scriptax/__init__.py
scriptax/main.py
scriptax/catalogs/ScriptCatalog.py
scriptax/catalogs/__init__.py
scriptax/drivers/Driver.py
scriptax/drivers/__init__.py
scriptax/drivers/builtin/Scriptax.py
scriptax/drivers/builtin/__init__.py
scriptax/exceptions/InvalidExpression.py
scriptax/exceptions/InvalidParameters.py
scriptax/exceptions/InvalidSymbolAccess.py
scriptax/exceptions/InvalidType.py
scriptax/exceptions/SymbolError.py
scriptax/exceptions/SymbolNotFound.py
scriptax/exceptions/__init__.py
scriptax/flow/ScriptaxExecutor.py
scriptax/flow/__init__.py
scriptax/grammar/__init__.py
scriptax/grammar/build/Ah3Lexer.py
scriptax/grammar/build/Ah3Listener.py
scriptax/grammar/build/Ah3Parser.py
scriptax/grammar/build/Ah3Visitor.py
scriptax/grammar/build/Ah4Lexer.py
scriptax/grammar/build/Ah4Listener.py
scriptax/grammar/build/Ah4Parser.py
scriptax/grammar/build/Ah4Visitor.py
scriptax/grammar/build/__init__.py
scriptax/models/AhOptions.py
scriptax/models/Attributes.py
scriptax/models/BlockStatus.py
scriptax/models/Callback.py
scriptax/models/CaseStatus.py
scriptax/models/Method.py
scriptax/models/Parameter.py
scriptax/models/Thread.py
scriptax/models/__init__.py
scriptax/parser/ModuleVisitor.py
scriptax/parser/SymbolTable.py
scriptax/parser/Visitor.py
scriptax/parser/__init__.py
scriptax/parser/symbols/ARISymbolTable.py
scriptax/parser/symbols/Symbol.py
scriptax/parser/symbols/SymbolScope.py
scriptax/parser/symbols/__init__.py
scriptax/parser/utils/BoilerPlate.py
scriptax/parser/utils/__init__.py
scriptax/tests/SymbolTableTest.py
scriptax/tests/__init__.py
scriptax/tests/pre_test.py
scriptax/tests/test_ahoptions.py
scriptax/tests/test_assignment.py
scriptax/tests/test_boolean.py
scriptax/tests/test_casting.py
scriptax/tests/test_comments.py
scriptax/tests/test_count.py
scriptax/tests/test_delete.py
scriptax/tests/test_dict.py
scriptax/tests/test_dict_signal.py
scriptax/tests/test_enum.py
scriptax/tests/test_error.py
scriptax/tests/test_float.py
scriptax/tests/test_for.py
scriptax-4.0.1.dist-info/LICENSE
scriptax-4.0.1.dist-info/METADATA
scriptax-4.0.1.dist-info/WHEEL
scriptax-4.0.1.dist-info/top_level.txt
scriptax-4.0.1.dist-info/RECORD
