Metadata-Version: 2.1
Name: scriptax
Version: 4.0.1
Summary: Scriptax is a powerful driver for the Apitax framework which exposes an automation first language used to quickly script together automation.
Home-page: https://github.com/Apitax/Scriptax
Author: Shawn Clake
Author-email: shawn.clake@gmail.com
License: UNKNOWN
Keywords: restful,api,commandtax,scriptax,apitax,drivers,plugins
Platform: UNKNOWN
Classifier: Programming Language :: Python :: 3
Classifier: Operating System :: OS Independent
Requires-Dist: antlr4-python3-runtime
Requires-Dist: apitaxcore (==3.0.9)
Requires-Dist: commandtax (==0.0.8)
Requires-Dist: pydantic
Requires-Dist: pytest
